aviationstack/__init__.py
aviationstack/api_helper.py
aviationstack/aviationstack_client.py
aviationstack/configuration.py
aviationstack/controllers/__init__.py
aviationstack/controllers/aircraft_types_controller.py
aviationstack/controllers/airlines_controller.py
aviationstack/controllers/airplanes_controller.py
aviationstack/controllers/airports_controller.py
aviationstack/controllers/base_controller.py
aviationstack/controllers/cities_controller.py
aviationstack/controllers/countries_controller.py
aviationstack/controllers/flight_future_schedules_controller.py
aviationstack/controllers/flight_schedules_controller.py
aviationstack/controllers/flights_controller.py
aviationstack/controllers/routes_controller.py
aviationstack/controllers/taxes_controller.py
aviationstack/exceptions/__init__.py
aviationstack/exceptions/api_exception.py
aviationstack/exceptions/error_response_exception.py
aviationstack/http/__init__.py
aviationstack/http/http_call_back.py
aviationstack/http/http_method_enum.py
aviationstack/http/http_request.py
aviationstack/http/http_response.py
aviationstack/http/auth/__init__.py
aviationstack/http/auth/custom_query_authentication.py
aviationstack/models/__init__.py
aviationstack/models/aircraft_info.py
aviationstack/models/aircraft_type.py
aviationstack/models/aircraft_type_response.py
aviationstack/models/airline.py
aviationstack/models/airline_info.py
aviationstack/models/airline_response.py
aviationstack/models/airplane.py
aviationstack/models/airplane_response.py
aviationstack/models/airport.py
aviationstack/models/airport_info.py
aviationstack/models/airport_response.py
aviationstack/models/city.py
aviationstack/models/city_response.py
aviationstack/models/country.py
aviationstack/models/country_response.py
aviationstack/models/error.py
aviationstack/models/flight.py
aviationstack/models/flight_info.py
aviationstack/models/flight_response.py
aviationstack/models/flight_schedule.py
aviationstack/models/flight_schedule_response.py
aviationstackserversdk-1.0.0.dist-info/licenses/LICENSE
aviationstackserversdk-1.0.0.dist-info/METADATA
aviationstackserversdk-1.0.0.dist-info/WHEEL
aviationstackserversdk-1.0.0.dist-info/top_level.txt
aviationstackserversdk-1.0.0.dist-info/RECORD
